gourav/__init__.py
gourav/main.py
hitler-0.1.3.dist-info/WHEEL
hitler-0.1.3.dist-info/METADATA
hitler-0.1.3.dist-info/RECORD
