Metadata-Version: 2.1
Name: hitler
Version: 0.1.3
Summary: this is random code unnecessary
Author: Gourav Saini
Requires-Python: >=3.8,<4.0
Classifier: Programming Language :: Python :: 3
Classifier: Programming Language :: Python :: 3.10
Classifier: Programming Language :: Python :: 3.8
Classifier: Programming Language :: Python :: 3.9
